README.md
setup.py
shareclass_yanyajun/__init__.py
shareclass_yanyajun/say_hello.py
shareclass_yanyajun.egg-info/PKG-INFO
shareclass_yanyajun.egg-info/SOURCES.txt
shareclass_yanyajun.egg-info/dependency_links.txt
shareclass_yanyajun.egg-info/top_level.txt